linkding_cli/__init__.py
linkding_cli/cli.py
linkding_cli/commands/__init__.py
linkding_cli/commands/bookmark.py
linkding_cli/commands/tag.py
linkding_cli/commands/user.py
linkding_cli/config.py
linkding_cli/const.py
linkding_cli/core.py
linkding_cli/errors.py
linkding_cli/helpers/__init__.py
linkding_cli/helpers/logging.py
linkding_cli/py.typed
linkding_cli/util/__init__.py
linkding_cli-2024.9.0.dist-info/LICENSE
linkding_cli-2024.9.0.dist-info/METADATA
linkding_cli-2024.9.0.dist-info/WHEEL
linkding_cli-2024.9.0.dist-info/entry_points.txt
linkding_cli-2024.9.0.dist-info/RECORD
