Metadata-Version: 2.1
Name: linkding_cli
Version: 2024.9.0
Summary: A CLI to interact with a linkding instance
Home-page: https://github.com/bachya/linkding-cli
License: MIT
Author: Aaron Bach
Author-email: bachya1208@gmail.com
Requires-Python: >=3.10,<4.0
Classifier: License :: OSI Approved :: MIT License
Classifier: Programming Language :: Python
Classifier: Programming Language :: Python :: 3
Classifier: Programming Language :: Python :: 3.10
Classifier: Programming Language :: Python :: 3.11
Classifier: Programming Language :: Python :: 3.12
Classifier: Programming Language :: Python :: Implementation :: CPython
Classifier: Programming Language :: Python :: Implementation :: PyPy
Requires-Dist: aiohttp (>=3.9.0)
Requires-Dist: aiolinkding (>=2023.10.0)
Requires-Dist: frozenlist (>=1.4.0,<2.0.0)
Requires-Dist: multidict (>=6.0.5)
Requires-Dist: ruamel.yaml (>=0.2.8)
Requires-Dist: shellingham (>=1.5.4)
Requires-Dist: typer[all] (>=0.6,<0.13)
Requires-Dist: yarl (>=1.9.2)
Project-URL: Bug Tracker, https://github.com/bachya/linkding_cli/issues
Project-URL: Changelog, https://github.com/bachya/linkding_cli/releases
Project-URL: Repository, https://github.com/bachya/linkding-cli
